naggetscipher/__init__.py
naggetscipher/cipher.py
naggetscipher-0.1.0.dist-info/LICENSE
naggetscipher-0.1.0.dist-info/METADATA
naggetscipher-0.1.0.dist-info/WHEEL
naggetscipher-0.1.0.dist-info/top_level.txt
naggetscipher-0.1.0.dist-info/RECORD
