Metadata-Version: 2.1
Name: naggetscipher
Version: 0.1.0
Summary: Библиотека для шифрования и дешифрования текста методом 'Наггетс'
Home-page: https://github.com/Lemonacho/naggetscipher
Author: Zaxece09
Author-email: akkb704@gmail.com
License: UNKNOWN
Platform: UNKNOWN
Classifier: Programming Language :: Python :: 3
Classifier: License :: OSI Approved :: MIT License
Classifier: Operating System :: OS Independent
Requires-Python: >=3.6
